kore_plugins_sanic/__init__.py
kore_plugins_sanic/application/__init__.py
kore_plugins_sanic/application/factories.py
kore_plugins_sanic/plugins/__init__.py
kore_plugins_sanic/plugins/application.py
kore_plugins_sanic-0.0.1.data/scripts/kore-sanic-run
kore_plugins_sanic-0.0.1.dist-info/DESCRIPTION.rst
kore_plugins_sanic-0.0.1.dist-info/entry_points.txt
kore_plugins_sanic-0.0.1.dist-info/METADATA
kore_plugins_sanic-0.0.1.dist-info/metadata.json
kore_plugins_sanic-0.0.1.dist-info/RECORD
kore_plugins_sanic-0.0.1.dist-info/top_level.txt
kore_plugins_sanic-0.0.1.dist-info/WHEEL
